drf_core/__init__.py
drf_core/admin.py
drf_core/apidoc.py
drf_core/apis.py
drf_core/apps.py
drf_core/assertion.py
drf_core/enums.py
drf_core/factories.py
drf_core/fields.py
drf_core/filtering.py
drf_core/models.py
drf_core/pagination.py
drf_core/sampling.py
drf_core/tests.py
drf_core/utils.py
drf_core-0.0.4.dist-info/LICENSE
drf_core-0.0.4.dist-info/METADATA
drf_core-0.0.4.dist-info/WHEEL
drf_core-0.0.4.dist-info/top_level.txt
drf_core-0.0.4.dist-info/RECORD
