Metadata-Version: 2.1
Name: drf-core
Version: 0.0.4
Summary: Provide reusable modules of Django REST framework.
Home-page: https://github.com/drf-tools/drf-core
Download-URL: https://github.com/drf-tools/drf-core/archive/v_001.tar.gz
Author: Huy Tran
Author-email: huy.tranquoc@asnet.com.vn
License: MIT
Keywords: API REST framework core modules
Classifier: Environment :: Web Environment
Classifier: Framework :: Django :: 3.0
Classifier: Intended Audience :: Developers
Classifier: License :: OSI Approved :: MIT License
Classifier: Operating System :: OS Independent
Classifier: Natural Language :: English
Classifier: Programming Language :: Python :: 3.6
Classifier: Programming Language :: Python :: 3.7
Classifier: Programming Language :: Python :: 3.8
Classifier: Topic :: Internet :: WWW/HTTP
Requires-Python: >=3.7.*
License-File: LICENSE
Requires-Dist: Django (>=3.0.4)
Requires-Dist: djangorestframework (>=3.11.0)
